management_commands/__init__.py
management_commands/conf.py
management_commands/core.py
management_commands/exceptions.py
management_commands/management.py
management_commands/py.typed
django_management_commands-1.1.0.dist-info/LICENSE
django_management_commands-1.1.0.dist-info/METADATA
django_management_commands-1.1.0.dist-info/WHEEL
django_management_commands-1.1.0.dist-info/top_level.txt
django_management_commands-1.1.0.dist-info/RECORD
