Metadata-Version: 2.1
Name: django-management-commands
Version: 1.1.0
Summary: Modular discovery, aliasing, and sequencing of Django commands
Author-email: Kamil Paduszyński <92403542+paduszyk@users.noreply.github.com>
Project-URL: Source, https://github.com/paduszyk/django-management-commands
Keywords: django,django-application,django-commands,django-management-commands
Classifier: Framework :: Django
Classifier: Framework :: Django :: 4.2
Classifier: Framework :: Django :: 5.0
Classifier: Framework :: Django :: 5.1
Classifier: Intended Audience :: Developers
Classifier: License :: OSI Approved :: MIT License
Classifier: Operating System :: OS Independent
Classifier: Programming Language :: Python
Classifier: Programming Language :: Python :: 3
Classifier: Programming Language :: Python :: 3 :: Only
Classifier: Programming Language :: Python :: 3.9
Classifier: Programming Language :: Python :: 3.10
Classifier: Programming Language :: Python :: 3.11
Classifier: Programming Language :: Python :: 3.12
Classifier: Topic :: Software Development :: Libraries :: Python Modules
Requires-Python: >=3.9
License-File: LICENSE
Requires-Dist: django <5.2,>=4.2
Requires-Dist: django-appconf ~=1.0
Requires-Dist: typing-extensions ~=4.12
Provides-Extra: dev
Requires-Dist: commitizen ~=3.29 ; extra == 'dev'
Requires-Dist: django-stubs[compatible-mypy] ~=5.0 ; extra == 'dev'
Requires-Dist: nox ==2024.4.15 ; extra == 'dev'
Requires-Dist: pre-commit ~=3.8 ; extra == 'dev'
Requires-Dist: pytest ~=8.3 ; extra == 'dev'
Requires-Dist: pytest-cov ~=5.0 ; extra == 'dev'
Requires-Dist: pytest-custom-exit-code ~=0.3 ; extra == 'dev'
Requires-Dist: pytest-django ~=4.9 ; extra == 'dev'
Requires-Dist: pytest-mock ~=3.14 ; extra == 'dev'
Requires-Dist: pytest-randomly ~=3.15 ; extra == 'dev'
Requires-Dist: ruff ~=0.6 ; extra == 'dev'
